odoo/addons/agreement/README.rst
odoo/addons/agreement/__init__.py
odoo/addons/agreement/__manifest__.py
odoo/addons/agreement/data/agreement_stage.xml
odoo/addons/agreement/data/agreement_type.xml
odoo/addons/agreement/data/ir_sequence.xml
odoo/addons/agreement/data/module_category.xml
odoo/addons/agreement/i18n/agreement.pot
odoo/addons/agreement/i18n/ar.po
odoo/addons/agreement/i18n/ca.po
odoo/addons/agreement/i18n/de.po
odoo/addons/agreement/i18n/fr.po
odoo/addons/agreement/i18n/it.po
odoo/addons/agreement/i18n/nl.po
odoo/addons/agreement/i18n/ru.po
odoo/addons/agreement/models/__init__.py
odoo/addons/agreement/models/account.py
odoo/addons/agreement/models/agreement.py
odoo/addons/agreement/models/agreement_appendix.py
odoo/addons/agreement/models/agreement_clause.py
odoo/addons/agreement/models/agreement_increasetype.py
odoo/addons/agreement/models/agreement_line.py
odoo/addons/agreement/models/agreement_recital.py
odoo/addons/agreement/models/agreement_renewaltype.py
odoo/addons/agreement/models/agreement_section.py
odoo/addons/agreement/models/agreement_serviceprofile.py
odoo/addons/agreement/models/agreement_stage.py
odoo/addons/agreement/models/agreement_subtype.py
odoo/addons/agreement/models/agreement_type.py
odoo/addons/agreement/models/product_template.py
odoo/addons/agreement/models/res_config_settings.py
odoo/addons/agreement/models/res_partner.py
odoo/addons/agreement/readme/CONFIGURE.rst
odoo/addons/agreement/readme/CONTRIBUTORS.rst
odoo/addons/agreement/readme/CREDITS.rst
odoo/addons/agreement/readme/DESCRIPTION.rst
odoo/addons/agreement/readme/ROADMAP.rst
odoo/addons/agreement/readme/USAGE.rst
odoo/addons/agreement/report/agreement.xml
odoo/addons/agreement/security/ir.model.access.csv
odoo/addons/agreement/security/res_groups.xml
odoo/addons/agreement/static/description/icon.png
odoo/addons/agreement/static/description/index.html
odoo/addons/agreement/views/agreement.xml
odoo/addons/agreement/views/agreement_appendix.xml
odoo11_addon_agreement-11.0.0.1.0.99.dev88.dist-info/METADATA
odoo11_addon_agreement-11.0.0.1.0.99.dev88.dist-info/WHEEL
odoo11_addon_agreement-11.0.0.1.0.99.dev88.dist-info/top_level.txt
odoo11_addon_agreement-11.0.0.1.0.99.dev88.dist-info/RECORD
